corpus_sc_toolkit/__init__.py
corpus_sc_toolkit/_sql/analysis/missing_dockets_in_opinions.sql
corpus_sc_toolkit/_sql/analysis/missing_phil_in_opinions.sql
corpus_sc_toolkit/_sql/analysis/missing_scra_in_opinions.sql
corpus_sc_toolkit/_sql/base/get_author_ids.sql
corpus_sc_toolkit/_sql/base/get_detail.sql
corpus_sc_toolkit/_sql/codes/events/search_unmaterialized.sql
corpus_sc_toolkit/_sql/codes/events/set_decision_id.sql
corpus_sc_toolkit/_sql/codes/events/set_statute_id.sql
corpus_sc_toolkit/_sql/codes/events/set_statute_unit_mp.sql
corpus_sc_toolkit/_sql/codes/get_base.sql
corpus_sc_toolkit/_sql/codes/list_event_statutes.sql
corpus_sc_toolkit/_sql/codes/list_unique_statute_category_idxes_from_events.sql
corpus_sc_toolkit/_sql/codes/update_statute_id.sql
corpus_sc_toolkit/_sql/decisions/chief_dates.sql
corpus_sc_toolkit/_sql/decisions/get_base.sql
corpus_sc_toolkit/_sql/decisions/inclusions/popular_citations.sql
corpus_sc_toolkit/_sql/decisions/inclusions/popular_statutes.sql
corpus_sc_toolkit/_sql/decisions/inclusions/read_opinions.sql
corpus_sc_toolkit/_sql/decisions/inclusions/update_decision_id.sql
corpus_sc_toolkit/_sql/decisions/limit_extract.sql
corpus_sc_toolkit/_sql/decisions/list_opinions_of_decision.sql
corpus_sc_toolkit/_sql/statutes/get_base.sql
corpus_sc_toolkit/_sql/statutes/list_affected_statutes.sql
corpus_sc_toolkit/_sql/statutes/list_affector_statutes.sql
corpus_sc_toolkit/_sql/statutes/references/src_ref_mp_list.sql
corpus_sc_toolkit/_sql/statutes/references/unique_statutes_list.sql
corpus_sc_toolkit/_sql/statutes/update_id.sql
corpus_sc_toolkit/config.py
corpus_sc_toolkit/decisions/__init__.py
corpus_sc_toolkit/decisions/_resources.py
corpus_sc_toolkit/decisions/decision.py
corpus_sc_toolkit/decisions/decision_fields.py
corpus_sc_toolkit/decisions/decision_fields_via_html.py
corpus_sc_toolkit/decisions/decision_fields_via_pdf.py
corpus_sc_toolkit/decisions/decision_opinion_segments.py
corpus_sc_toolkit/decisions/decision_opinions.py
corpus_sc_toolkit-0.2.4.dist-info/WHEEL
corpus_sc_toolkit-0.2.4.dist-info/METADATA
corpus_sc_toolkit-0.2.4.dist-info/RECORD
