Metadata-Version: 2.1
Name: corpus-sc-toolkit
Version: 0.2.4
Summary: Toolkit to process component elements of a Philippine Supreme Court decision.
Home-page: https://mv3.dev
License: MIT
Author: Marcelino G. Veloso III
Author-email: mars@veloso.one
Requires-Python: >=3.11,<4.0
Classifier: Development Status :: 4 - Beta
Classifier: Framework :: Pydantic
Classifier: Framework :: Pytest
Classifier: Intended Audience :: Legal Industry
Classifier: License :: OSI Approved :: MIT License
Classifier: Programming Language :: Python :: 3
Classifier: Programming Language :: Python :: 3.11
Classifier: Programming Language :: Python :: 3.11
Classifier: Typing :: Typed
Requires-Dist: citation-utils (>=0.2.8,<0.3.0)
Requires-Dist: corpus-pax (>=0.1.24,<0.2.0)
Requires-Dist: markdownify (>=0.11.6,<0.12.0)
Requires-Dist: pebble (>=5.0.3,<6.0.0)
Requires-Dist: pylts (>=0.0.8,<0.0.9)
Requires-Dist: statute-trees (>=0.1.4,<0.2.0)
Requires-Dist: unidecode (>=1.3.6,<2.0.0)
Project-URL: Documentation, https://mv3.dev/corpus-sc-toolkit
Project-URL: Repository, https://github.com/justmars/corpus-sc-toolkit
